src/vsm/register.py
src/vsm/setup.py
src/vsm/doc/source/conf.py
src/vsm/unit_tests/__init__.py
src/vsm/vsm/__init__.py
src/vsm/vsm/spatial.py
src/vsm/vsm/split.py
src/vsm/vsm/structarr.py
src/vsm/vsm/zipfile.py
src/vsm/vsm/corpus/__init__.py
src/vsm/vsm/corpus/base.py
src/vsm/vsm/corpus/util/__init__.py
src/vsm/vsm/corpus/util/corpusbuilders.py
src/vsm/vsm/exceptions/__init__.py
src/vsm/vsm/exceptions/compatibility.py
src/vsm/vsm/extensions/__init__.py
src/vsm/vsm/extensions/editions.py
src/vsm/vsm/extensions/htrc.py
src/vsm/vsm/extensions/inpho.py
src/vsm/vsm/extensions/ldasentences.py
src/vsm/vsm/extensions/multi_k.py
src/vsm/vsm/extensions/trans.py
src/vsm/vsm/extensions/clustering/__init__.py
src/vsm/vsm/extensions/clustering/manifold.py
src/vsm/vsm/extensions/clustering/plotting.py
src/vsm/vsm/extensions/corpusbuilders/__init__.py
src/vsm/vsm/extensions/corpusbuilders/corpusbuilders.py
src/vsm/vsm/extensions/corpusbuilders/corpusstreamers.py
src/vsm/vsm/extensions/corpusbuilders/util.py
src/vsm/vsm/extensions/interop/__init__.py
src/vsm/vsm/extensions/interop/ldac.py
src/vsm/vsm/extensions/interop/mallet.py
src/vsm/vsm/extensions/interop/weka.py
src/vsm/vsm/extensions/lda_py4j/org/knowceans/gibbstest/FileReadWrite.py
src/vsm/vsm/extensions/lda_py4j/org/knowceans/gibbstest/LdaRoutine.py
src/vsm/vsm/extensions/mahout/mahout.py
src/vsm/vsm/model/__init__.py
src/vsm/vsm/model/base.py
src/vsm/vsm/model/beaglecomposite.py
src/vsm/vsm/model/beaglecontext.py
src/vsm/vsm/model/beagleenvironment.py
src/vsm/vsm/model/beagleorder.py
src/vsm/vsm/model/lda.py
src/vsm/vsm/model/ldacgs.py
src/vsm/vsm/model/ldacgsmulti.py
src/vsm/vsm/model/ldacgsseq.py
src/vsm/vsm/model/ldaexact.py
src/vsm/vsm/model/ldafunctions.py
src/vsm/vsm/model/ldagibbs.py
src/vsm/vsm/model/lsa.py
src/vsm/vsm/model/tf.py
src/vsm/vsm/model/tfidf.py
src/vsm/vsm/viewer/__init__.py
src/vsm/vsm/viewer/beagleviewer.py
src/vsm/vsm/viewer/labeleddata.py
src/vsm/vsm/viewer/ldacgsviewer.py
htrc_vsm-0.4.15.1.dist-info/METADATA
htrc_vsm-0.4.15.1.dist-info/WHEEL
htrc_vsm-0.4.15.1.dist-info/licenses/LICENSE.txt
htrc_vsm-0.4.15.1.dist-info/RECORD
