Metadata-Version: 2.1
Name: htrc_vsm
Version: 0.4.15.1
Summary: HTRC rework of the InPHO vsm package.
Project-URL: Homepage, https://github.com/htrc/vsm
Project-URL: Bug Tracker, https://github.com/htrc/vsm/issues
Author-email: Damien Thomas <damien.thomas.0214@gmail.com>, Samitha Liyanage <shliyana@indiana.edu>
License-File: LICENSE.txt
Classifier: Development Status :: 5 - Production/Stable
Classifier: Environment :: Console
Classifier: Intended Audience :: Developers
Classifier: Intended Audience :: Science/Research
Classifier: License :: OSI Approved :: MIT License
Classifier: Operating System :: OS Independent
Classifier: Programming Language :: Python
Classifier: Programming Language :: Python :: 2
Classifier: Programming Language :: Python :: 3
Classifier: Topic :: Scientific/Engineering :: Artificial Intelligence
Classifier: Topic :: Software Development :: Libraries :: Python Modules
Classifier: Topic :: Text Processing :: Linguistic
Requires-Python: >=3.6
